lazyspider/__init__.py
lazyspider/lazyagent.py
lazyspider/lazyheaders.py
lazyspider/lazystore.py
lazyspider-0.0.3.dist-info/DESCRIPTION.rst
lazyspider-0.0.3.dist-info/METADATA
lazyspider-0.0.3.dist-info/RECORD
lazyspider-0.0.3.dist-info/WHEEL
lazyspider-0.0.3.dist-info/metadata.json
lazyspider-0.0.3.dist-info/top_level.txt
