Metadata-Version: 2.0
Name: lazyspider
Version: 0.0.3
Summary: Powerful spider tools
Home-page: https://github.com/Ehco1996/lazySpider
Author: Ehco1996
Author-email: zh19960202@gmial.com
License: GPLv3
Keywords: spider headers mysql
Platform: UNKNOWN
Classifier: Development Status :: 2 - Pre-Alpha
Classifier: Programming Language :: Python :: 3.3
Classifier: Programming Language :: Python :: 3.4
Classifier: Programming Language :: Python :: 3.5
Classifier: Programming Language :: Python :: 3.6
Requires-Dist: pymysql
